zhpr/__init__.py
zhpr/core.py
zhpr/predict.py
g_zhpr-0.1.3.dist-info/METADATA
g_zhpr-0.1.3.dist-info/WHEEL
g_zhpr-0.1.3.dist-info/RECORD
