Metadata-Version: 2.1
Name: g-zhpr
Version: 0.1.3
Summary: 
Author: Philip Huang
Author-email: p208p2002@gmail.com
Requires-Python: >=3.8,<4.0
Classifier: Programming Language :: Python :: 3
Classifier: Programming Language :: Python :: 3.8
Classifier: Programming Language :: Python :: 3.9
Classifier: Programming Language :: Python :: 3.10
Classifier: Programming Language :: Python :: 3.11
Requires-Dist: openpyxl (>=3.0.10,<4.0.0)
Requires-Dist: pandas (>=1.5.1,<2.0.0)
Requires-Dist: scikit-learn (>=1.1.3,<2.0.0)
Requires-Dist: seqeval (>=1.2.2,<2.0.0)
Requires-Dist: transformers (>=4.24.0,<5.0.0)
